zhenglin/__init__.py
zhenglin/accelerate/config.yaml
zhenglin/accelerate/config_accelerate.yaml
zhenglin/accelerate/dataset.py
zhenglin/accelerate/train.py
zhenglin/accelerate/networks/unet.py
zhenglin/filesystem/filesystem.py
zhenglin/lightning/config.yaml
zhenglin/lightning/dataset.py
zhenglin/lightning/train.py
zhenglin/lightning/networks/unet.py
zhenglin/networks/cyclegan.py
zhenglin/networks/ddpm.py
zhenglin/networks/deblurgan.py
zhenglin/networks/discriminator.py
zhenglin/networks/edsr.py
zhenglin/networks/esrgan.py
zhenglin/networks/mobilevit.py
zhenglin/networks/noise2void.py
zhenglin/networks/pix2pix.py
zhenglin/networks/rcan.py
zhenglin/networks/resnet.py
zhenglin/networks/restormer.py
zhenglin/networks/rrdb.py
zhenglin/networks/squeezenet.py
zhenglin/networks/srdrm.py
zhenglin/networks/srgan.py
zhenglin/networks/swin_unet.py
zhenglin/networks/swinir.py
zhenglin/networks/trans_unet.py
zhenglin/networks/u2net.py
zhenglin/networks/unet.py
zhenglin/networks/unet_attn.py
zhenglin/networks/unet_vanilla.py
zhenglin/networks/unets_lite.py
zhenglin/networks_/aae/__init__.py
zhenglin/networks_/aae/aae.py
zhenglin/networks_/acgan/__init__.py
zhenglin/networks_/acgan/acgan.py
zhenglin/networks_/began/__init__.py
zhenglin/networks_/began/began.py
zhenglin/networks_/bgan/__init__.py
zhenglin/networks_/bgan/bgan.py
zhenglin/networks_/bicyclegan/__init__.py
zhenglin/networks_/bicyclegan/bicyclegan.py
zhenglin/networks_/bicyclegan/datasets.py
zhenglin/networks_/bicyclegan/network.py
zhenglin/networks_/ccgan/__init__.py
zhenglin/networks_/ccgan/ccgan.py
zhenglin/networks_/ccgan/datasets.py
zhenglin/networks_/ccgan/network.py
zhenglin/networks_/cgan/__init__.py
zhenglin/networks_/cgan/cgan.py
zhenglin/networks_/cluster_gan/__init__.py
zhenglin/networks_/cluster_gan/clustergan.py
zhenglin/networks_/cogan/__init__.py
zhenglin/networks_/cogan/cogan.py
zhenglin/networks_/cogan/mnistm.py
zhenglin/networks_/context_encoder/__init__.py
zhenglin-3.0.2.dist-info/METADATA
zhenglin-3.0.2.dist-info/WHEEL
zhenglin-3.0.2.dist-info/licenses/LICENSE
zhenglin-3.0.2.dist-info/RECORD
