Metadata-Version: 2.4
Name: zhenglin
Version: 3.0.2
Summary: A deep-learning package contains a set of well-organized deep-neural networks&tools.
Project-URL: Homepage, https://github.com/ZhenglinPan/zhenglin-package
Project-URL: Bug Tracker, https://github.com/ZhenglinPan/zhenglin-package/issues
Author-email: Zhenglin <aidenhpan@gmail.com>
License-File: LICENSE
Classifier: License :: OSI Approved :: MIT License
Classifier: Operating System :: OS Independent
Classifier: Programming Language :: Python :: 3
Requires-Python: >=3.8
